msb_client/ComplexDataFormat.py
msb_client/DataFormat.py
msb_client/DataType.py
msb_client/Event.py
msb_client/Function.py
msb_client/MsbClient.py
msb_client/__init__.py
msb_client/event_schema.json
msb_client/function_schema.json
vfk.msb.client.library.python-1.0.dist-info/METADATA
vfk.msb.client.library.python-1.0.dist-info/RECORD
vfk.msb.client.library.python-1.0.dist-info/WHEEL
vfk.msb.client.library.python-1.0.dist-info/top_level.txt
