Metadata-Version: 2.1
Name: vfk.msb.client.library.python
Version: 1.0
Summary: A library to connect to the MSB of VirtualFortKnox
Home-page: https://www.virtualfortknox.de/
Author: Daniel Stock
Author-email: daniel.stock@ipa.fraunhofer.de
License: UNKNOWN
Platform: UNKNOWN
Requires-Dist: websocket-client
Requires-Dist: jsonschema
Requires-Dist: jsonpickle
Requires-Dist: enum34
